marketing_urls/__init__.py
marketing_urls/admin.py
marketing_urls/models.py
marketing_urls/tests.py
marketing_urls/urls.py
marketing_urls/utils.py
marketing_urls/views.py
marketing_urls/migrations/0001_initial.py
marketing_urls/migrations/__init__.py
django_marketing_urls-1.0.1.dist-info/LICENSE
django_marketing_urls-1.0.1.dist-info/METADATA
django_marketing_urls-1.0.1.dist-info/WHEEL
django_marketing_urls-1.0.1.dist-info/top_level.txt
django_marketing_urls-1.0.1.dist-info/zip-safe
django_marketing_urls-1.0.1.dist-info/RECORD
