Metadata-Version: 2.1
Name: django-marketing-urls
Version: 1.0.1
Summary: An app to generate marketing urls for Django projects. 
Home-page: https://github.com/laonan/django-marketing-urls
Author: Laonan
Author-email: hello@laonan.net
Project-URL: Bug Tracker, https://github.com/laonan/django-marketing-urls/issues
Classifier: Programming Language :: Python :: 3
Classifier: License :: OSI Approved :: MIT License
Classifier: Operating System :: OS Independent
Requires-Python: >=3.6
License-File: LICENSE
Requires-Dist: Django (>=2.0.13)
Requires-Dist: urltoken (>=1.0.0)
